ssmiley_autoidm_learn_poetry/__init__.py
ssmiley_autoidm_learn_poetry/__main__.py
ssmiley_autoidm_learn_poetry/hello_world.py
ssmiley_autoidm_learn_poetry-0.2.0.dist-info/METADATA
ssmiley_autoidm_learn_poetry-0.2.0.dist-info/WHEEL
ssmiley_autoidm_learn_poetry-0.2.0.dist-info/RECORD
